blogue/__init__.py
blogue/__main__.py
blogue-0.2.0.dist-info/METADATA
blogue-0.2.0.dist-info/WHEEL
blogue-0.2.0.dist-info/dependency_links.txt
blogue-0.2.0.dist-info/entry_points.txt
blogue-0.2.0.dist-info/top_level.txt
blogue-0.2.0.dist-info/RECORD
